storer/__init__.py
storer/storer.py
storer/compressor/__init__.py
storer/compressor/compressor.py
storer/tests/__init__.py
storer/tests/tests.py
storer-1.0.8.dist-info/LICENSE.txt
storer-1.0.8.dist-info/METADATA
storer-1.0.8.dist-info/WHEEL
storer-1.0.8.dist-info/top_level.txt
storer-1.0.8.dist-info/RECORD
