Metadata-Version: 2.1
Name: storer
Version: 1.0.8
Summary: Minimalist storage class for any purpose.
Home-page: https://github.com/AlexanderDKazakov/Storer
Author: Alexander D. Kazakov
Author-email: alexander.d.kazakov@gmail.com
License: MIT
Keywords: store,pickle
Platform: UNKNOWN
Classifier: Development Status :: 4 - Beta
Classifier: Intended Audience :: Developers
Classifier: Topic :: Software Development :: Build Tools
Classifier: License :: OSI Approved :: MIT License
Classifier: Programming Language :: Python :: 3
Classifier: Programming Language :: Python :: 3.8
Classifier: Programming Language :: Python :: 3.9
Requires-Python: >=3.7
